{
  "workbench.colorTheme": "Solarized Dark",
  "workbench.fontSize": 40,
  "editor.wordWrap": "on",
  "gitlens.advanced.messages": {
    "suppressShowKeyBindingsNotice": true
  },
  "gitlens.defaultDateStyle": "absolute",
  "window.zoomLevel": 0,
  "editor.formatOnSave": true,
  "[clojure]": {
    "editor.wordSeparators": "\t ()\"':,;~@#$%^&{}[]`",
    "editor.autoClosingBrackets": "always",
    "editor.autoClosingQuotes": "always",
    "editor.formatOnType": true,
    "editor.autoIndent": true,
    "editor.formatOnPaste": true,
    "files.trimTrailingWhitespace": false,
    "editor.matchBrackets": false,
  },
  "[clojurescript]": {
    "editor.formatOnSave": false
  },
  "[html]": {
    "editor.formatOnSave": false
  },
  "eslint.autoFixOnSave": true,
  "eslint.alwaysShowStatus": true,
  "python.formatting.provider": "autopep8",
  "terminal.integrated.rendererType": "dom",
  "python.linting.pylintArgs": [
    "--load-plugins=pylint_django"
  ],
  "editor.fontSize": 18,
  "editor.minimap.enabled": false
}
